cloudbrain_client/__init__.py
cloudbrain_client/ai_conversation_helper.py
cloudbrain_client/ai_websocket_client.py
cloudbrain_client/cloudbrain_client.py
cloudbrain_client/cloudbrain_collaboration_helper.py
cloudbrain_client/cloudbrain_quick.py
cloudbrain_client/message_poller.py
cloudbrain_client-1.1.1.dist-info/METADATA
cloudbrain_client-1.1.1.dist-info/WHEEL
cloudbrain_client-1.1.1.dist-info/entry_points.txt
cloudbrain_client-1.1.1.dist-info/top_level.txt
cloudbrain_client-1.1.1.dist-info/RECORD
